{
   "mixins": "stonehearth:mixins:placed_object",
   "components": {
      "model_variants": {
         "default": {
            "models": [
               "file(candelabra_stone.qb)"
            ]
         }
      },
      "mob": {
         "model_origin": { "x": -0.7, "y": 0, "z": 0.5 },
         "region_origin": { "x": 0.7, "y": 0, "z": 0.5 }
      },
      "render_info": {
         "scale": 0.1
      },
      "unit_info": {
         "display_name": "i18n(lodewall-lights:entities.decoration.candelabra_stone_ghost.name)",
         "description": "i18n(lodewall-lights:entities.decoration.candelabra_stone_ghost.description)",
         "icon": "file(candelabra_stone.png)"
      },
      "stonehearth:material": {
         "tags": "light_source crafted stone"
      }
   }
}